wsgi_to_zpm/__init__.py
wsgi_to_zpm/__main__.py
wsgi_to_zpm/module.py
wsgi_to_zpm/module.xml
wsgi_to_zpm/prompt.py
wsgi_to_zpm/web_app.py
wsgi_to_zpm/wsgi_finder.py
wsgi_to_zpm-0.1.0.dist-info/entry_points.txt
wsgi_to_zpm-0.1.0.dist-info/licenses/LICENSE
wsgi_to_zpm-0.1.0.dist-info/WHEEL
wsgi_to_zpm-0.1.0.dist-info/METADATA
wsgi_to_zpm-0.1.0.dist-info/RECORD
