Metadata-Version: 2.4
Name: wsgi_to_zpm
Version: 0.1.0
Summary: Generate ZPM/IPM module.xml from an existing WSGI project.
Author-email: jamerfort <jamerfort+pypi@gmail.com>
License-Expression: MIT
License-File: LICENSE
Requires-Dist: lxml
